biontfy/__init__.py
biontfy/notification_item.py
biontfy/notification_manager.py
biontfy/notification_utilities.py
biontfy/resources/msg_incoming.mp3
biontfy/resources/msr.mp3
biontfy/resources/userpic1.png
biontfy/resources/userpic2.png
biontfy/resources/fonts/Vazirmatn-Regular.ttf
biontfy-2.0.0.dist-info/METADATA
biontfy-2.0.0.dist-info/WHEEL
biontfy-2.0.0.dist-info/top_level.txt
biontfy-2.0.0.dist-info/RECORD
