Metadata-Version: 2.4
Name: biontfy
Version: 2.0.0
Summary: A customizable PyQt6 notification library based on a Telegram-like design.
Home-page: https://github.com/yourusername/pyqt-custom-notify
Author: Bitro dev
Classifier: Programming Language :: Python :: 3
Classifier: License :: OSI Approved :: MIT License
Classifier: Operating System :: OS Independent
Requires-Python: >=3.8
Requires-Dist: PyQt6
Requires-Dist: pydub
Dynamic: author
Dynamic: classifier
Dynamic: description
Dynamic: description-content-type
Dynamic: home-page
Dynamic: requires-dist
Dynamic: requires-python
Dynamic: summary
